<?xml version='1.0' encoding='utf-8'?>
<data><item><field_0>JS00100200305</field_0><field_1>Jack</field_1><field_2>Sparrow</field_2><field_3>js@blackpearl.com</field_3><field_4>Web Dev Fundamentals</field_4><field_5>21</field_5></item><item><field_0>BC00100200326</field_0><field_1>Benedict</field_1><field_2>Cumberbatch</field_2><field_3>benny@strange.com</field_3><field_4>Files</field_4><field_5>24</field_5></item><item><field_0>JS00100200305</field_0><field_1>Jack</field_1><field_2>Sparrow</field_2><field_3>js@blackpearl.com</field_3><field_4>Web Dev Frameworks</field_4><field_5>26</field_5></item></data>